{
  "video": [
    {
      "_createdAt": "2023-01-26T01:57:12Z",
      "_id": "musiNgaCJCFj96pZgLaL1j",
      "_rev": "musiNgaCJCFj96pZgLaKyJ",
      "_type": "video",
      "_updatedAt": "2023-01-26T01:57:12Z",
      "link": "https://youtu.be/K1jqqIDpUV4",
      "title": "Making a Pure CSS Stopwatch with @property",
      "where": "YouTube"
    },
    {
      "_createdAt": "2023-01-26T01:57:12Z",
      "_id": "JT25mgDZyxUcyfTT8JG46I",
      "_rev": "JT25mgDZyxUcyfTT8JG41x",
      "_type": "video",
      "_updatedAt": "2023-01-26T01:57:12Z",
      "link": "https://youtu.be/fgllse9q3Yw",
      "title": "Animate Bendy Strings with GreenSock",
      "where": "YouTube"
    },
    {
      "_createdAt": "2023-01-13T11:03:18Z",
      "_id": "8DAcJLIO7Kw5bjud3vnEN3",
      "_rev": "4aJWHuCbD1g0KTYU9T4eRY",
      "_type": "video",
      "_updatedAt": "2023-01-21T13:52:53Z",
      "description": "",
      "link": "https://twitter.com/jh3yy/status/1517629642064150529",
      "tags": null,
      "title": "Speedy CSS Tip – Boujee Text",
      "when": "2022-04-22"
    }
  ]
}